draews/__init__.py
draews/draews.py
draews/models.py
draews-0.1.1.dist-info/LICENSE
draews-0.1.1.dist-info/METADATA
draews-0.1.1.dist-info/WHEEL
draews-0.1.1.dist-info/RECORD
